minilin/__init__.py
minilin/cli.py
minilin/config.py
minilin/pipeline.py
minilin/data/__init__.py
minilin/data/analyzer.py
minilin/data/audio_augmenter.py
minilin/data/audio_loader.py
minilin/data/augmenter.py
minilin/data/backtranslation.py
minilin/data/image_augmenter.py
minilin/data/image_loader.py
minilin/data/loader.py
minilin/deployment/__init__.py
minilin/deployment/api_server.py
minilin/deployment/exporter.py
minilin/models/__init__.py
minilin/models/audio_trainer.py
minilin/models/few_shot.py
minilin/models/image_trainer.py
minilin/models/multimodal.py
minilin/models/trainer.py
minilin/models/zoo.py
minilin/optimization/__init__.py
minilin/optimization/compressor.py
minilin/optimization/distillation.py
minilin/optimization/pruner.py
minilin/optimization/quantizer.py
minilin/utils/__init__.py
minilin/utils/config.py
minilin/utils/logger.py
minilin-0.4.1.dist-info/licenses/LICENSE
minilin-0.4.1.dist-info/METADATA
minilin-0.4.1.dist-info/WHEEL
minilin-0.4.1.dist-info/top_level.txt
minilin-0.4.1.dist-info/RECORD
