Metadata-Version: 2.4
Name: minilin
Version: 0.4.1
Summary: A universal low-resource deep learning framework - Learn More with Less
Home-page: https://github.com/minilin-ai/minilin
Author: MiniLin Team
Author-email: MiniLin Team <contact@minilin.ai>
License: MIT
Project-URL: Homepage, https://github.com/minilin-ai/minilin
Project-URL: Documentation, https://minilin.readthedocs.io
Project-URL: Repository, https://github.com/minilin-ai/minilin
Project-URL: Bug Tracker, https://github.com/minilin-ai/minilin/issues
Keywords: deep-learning,machine-learning,low-resource,edge-ai,model-compression
Classifier: Development Status :: 3 - Alpha
Classifier: Intended Audience :: Developers
Classifier: Intended Audience :: Science/Research
Classifier: License :: OSI Approved :: MIT License
Classifier: Programming Language :: Python :: 3
Classifier: Programming Language :: Python :: 3.8
Classifier: Programming Language :: Python :: 3.9
Classifier: Programming Language :: Python :: 3.10
Classifier: Programming Language :: Python :: 3.11
Classifier: Topic :: Scientific/Engineering :: Artificial Intelligence
Requires-Python: >=3.8
License-File: LICENSE
Dynamic: author
Dynamic: home-page
Dynamic: license-file
Dynamic: requires-python
